{"buffers":[{"byteLength":0,"uri":"data:application/octet-stream;base64,"}],"data":{"metadata":{"nodes":{"Node-1":{"position":{"x":830,"y":179}},"Node-10":{"position":{"x":-1159,"y":17}},"Node-11":{"position":{"x":-1445,"y":-76}},"Node-12":{"position":{"x":-888,"y":362}},"Node-14":{"position":{"x":-1238,"y":197}},"Node-15":{"position":{"x":-930,"y":179}},"Node-17":{"position":{"x":-1031,"y":599}},"Node-19":{"position":{"x":6,"y":330}},"Node-2":{"position":{"x":578,"y":144}},"Node-20":{"position":{"x":197,"y":318}},"Node-21":{"position":{"x":-24,"y":-107}},"Node-22":{"position":{"x":-31,"y":193}},"Node-24":{"position":{"x":-1954,"y":352}},"Node-25":{"position":{"x":-2133,"y":360}},"Node-26":{"position":{"x":-1740,"y":225}},"Node-27":{"position":{"x":-1938,"y":217}},"Node-28":{"position":{"x":-1267,"y":617}},"Node-29":{"position":{"x":-266,"y":-80}},"Node-3":{"position":{"x":195,"y":-173}},"Node-30":{"position":{"x":-2429,"y":119}},"Node-31":{"position":{"x":-1879,"y":561}},"Node-32":{"position":{"x":-1483,"y":406}},"Node-33":{"position":{"x":-1664,"y":463}},"Node-34":{"position":{"x":-1221,"y":415}},"Node-4":{"position":{"x":-31,"y":31}},"Node-5":{"position":{"x":-213,"y":39}},"Node-6":{"position":{"x":-418,"y":46}},"Node-7":{"position":{"x":-625,"y":84}},"Node-8":{"position":{"x":-836,"y":597}},"Node-9":{"position":{"x":-1488,"y":102}}}},"nodes":{"Node-1":{"type":"github.com/EliCDavis/polyform/nodes.Struct[github.com/EliCDavis/polyform/formats/gltf.ManifestNode]","assignedInput":{"Models.0":{"id":"Node-2","port":"Out"}}},"Node-10":{"type":"github.com/EliCDavis/polyform/nodes.Struct[github.com/EliCDavis/polyform/math/vector2.AddToArrayNode[float64]]","assignedInput":{"Amount":{"id":"Node-11","port":"Value"},"Array":{"id":"Node-9","port":"Vector 2"}}},"Node-11":{"type":"github.com/EliCDavis/polyform/generator/parameter.Value[github.com/EliCDavis/vector/vector2.Vector[float64]]","data":{"name":"","description":"","currentValue":{"x":0.5,"y":0.5}}},"Node-12":{"type":"github.com/EliCDavis/polyform/generator/parameter.Value[bool]","data":{"name":"","description":"","currentValue":true}},"Node-14":{"type":"github.com/EliCDavis/polyform/nodes.Struct[github.com/EliCDavis/polyform/math/vector3.SelectArray[float64]]","assignedInput":{"In":{"id":"Node-9","port":"Vector 3"}}},"Node-15":{"type":"github.com/EliCDavis/polyform/nodes.Struct[github.com/EliCDavis/polyform/math.AddToArrayNode[float64]]","assignedInput":{"Array":{"id":"Node-14","port":"Y"},"In":{"id":"Node-34","port":"Float 64"}}},"Node-17":{"type":"github.com/EliCDavis/polyform/nodes.Struct[github.com/EliCDavis/polyform/math/vector2.NewNode[int]]","assignedInput":{"X":{"id":"Node-28","port":"Value"},"Y":{"id":"Node-28","port":"Value"}}},"Node-19":{"type":"github.com/EliCDavis/polyform/nodes.Struct[github.com/EliCDavis/polyform/modeling/primitives.QuadSphereNode]"},"Node-2":{"type":"github.com/EliCDavis/polyform/nodes.Struct[github.com/EliCDavis/polyform/formats/gltf.ModelNode]","assignedInput":{"Material":{"id":"Node-3","port":"Out"},"Mesh":{"id":"Node-20","port":"Out"}}},"Node-20":{"type":"github.com/EliCDavis/polyform/nodes.Struct[github.com/EliCDavis/polyform/modeling/meshops.SmoothNormalsImplicitWeldNode]","assignedInput":{"Mesh":{"id":"Node-19","port":"Out"}}},"Node-21":{"type":"github.com/EliCDavis/polyform/nodes.Struct[github.com/EliCDavis/polyform/math.ZeroNode]"},"Node-22":{"type":"github.com/EliCDavis/polyform/generator/parameter.Value[float64]","data":{"name":"","description":"","currentValue":0.25}},"Node-24":{"type":"github.com/EliCDavis/polyform/nodes.Struct[github.com/EliCDavis/polyform/math.InverseNode[float64]]","assignedInput":{"In":{"id":"Node-25","port":"Out"}}},"Node-25":{"type":"github.com/EliCDavis/polyform/nodes.Struct[github.com/EliCDavis/polyform/math.IntToFloatNode]","assignedInput":{"In":{"id":"Node-30","port":"Value"}}},"Node-26":{"type":"github.com/EliCDavis/polyform/nodes.Struct[github.com/EliCDavis/polyform/math.SubtractNode[float64]]","assignedInput":{"A":{"id":"Node-27","port":"Float 64"},"B":{"id":"Node-24","port":"Multiplicative"}}},"Node-27":{"type":"github.com/EliCDavis/polyform/nodes.Struct[github.com/EliCDavis/polyform/math.OneNode]"},"Node-28":{"type":"github.com/EliCDavis/polyform/generator/variable.VariableReferenceNode[int]","variable":"Texture Resolution"},"Node-29":{"type":"github.com/EliCDavis/polyform/generator/variable.VariableReferenceNode[float64]","variable":"Dimple Depth"},"Node-3":{"type":"github.com/EliCDavis/polyform/nodes.Struct[github.com/EliCDavis/polyform/formats/gltf.MaterialNode]","assignedInput":{"Metallic Factor":{"id":"Node-21","port":"Float 64"},"Normal Texture":{"id":"Node-4","port":"Out"},"Roughness Factor":{"id":"Node-22","port":"Value"}}},"Node-30":{"type":"github.com/EliCDavis/polyform/generator/variable.VariableReferenceNode[int]","variable":"Dimple Count"},"Node-31":{"type":"github.com/EliCDavis/polyform/generator/variable.VariableReferenceNode[int]","variable":"Dimple Count"},"Node-32":{"type":"github.com/EliCDavis/polyform/nodes.Struct[github.com/EliCDavis/polyform/math.InverseNode[float64]]","assignedInput":{"In":{"id":"Node-33","port":"Out"}}},"Node-33":{"type":"github.com/EliCDavis/polyform/nodes.Struct[github.com/EliCDavis/polyform/math.IntToFloatNode]","assignedInput":{"In":{"id":"Node-31","port":"Value"}}},"Node-34":{"type":"github.com/EliCDavis/polyform/nodes.Struct[github.com/EliCDavis/polyform/math.HalfNode[float64]]","assignedInput":{"In":{"id":"Node-32","port":"Multiplicative"}}},"Node-4":{"type":"github.com/EliCDavis/polyform/nodes.Struct[github.com/EliCDavis/polyform/formats/gltf.NormalTextureNode]","assignedInput":{"Scale":{"id":"Node-29","port":"Value"},"Texture":{"id":"Node-5","port":"Out"}}},"Node-5":{"type":"github.com/EliCDavis/polyform/nodes.Struct[github.com/EliCDavis/polyform/formats/gltf.TextureNode]","assignedInput":{"Image":{"id":"Node-6","port":"Image"}}},"Node-6":{"type":"github.com/EliCDavis/polyform/nodes.Struct[github.com/EliCDavis/polyform/drawing/texturing/normals.FromNormalMapNode]","assignedInput":{"Normals":{"id":"Node-7","port":"Normal Map"}}},"Node-7":{"type":"github.com/EliCDavis/polyform/nodes.Struct[github.com/EliCDavis/polyform/drawing/texturing/normals.DrawSpheresNode]","assignedInput":{"Positions":{"id":"Node-10","port":"Out"},"Radii":{"id":"Node-15","port":"Sums"},"Subtract":{"id":"Node-12","port":"Value"},"Texture":{"id":"Node-8","port":"Normal Map"}}},"Node-8":{"type":"github.com/EliCDavis/polyform/nodes.Struct[github.com/EliCDavis/polyform/drawing/texturing/normals.NewNode]","assignedInput":{"Dimensions":{"id":"Node-17","port":"Out"}}},"Node-9":{"type":"github.com/EliCDavis/polyform/nodes.Struct[github.com/EliCDavis/polyform/modeling/repeat.GridNode]","assignedInput":{"Columns":{"id":"Node-30","port":"Value"},"Height":{"id":"Node-26","port":"Float"},"Rows":{"id":"Node-30","port":"Value"},"Width":{"id":"Node-26","port":"Float"}}}},"producers":{},"variables":{"subgroups":{},"variables":{"Dimple Count":{"description":"How many dimples are on the rows/columns on the sides of the ball","data":{"type":"int","value":15}},"Dimple Depth":{"description":"A value between 0 and 1 indicating how deep the dimples on the ball are","data":{"type":"float64","value":0.4}},"Texture Resolution":{"description":"","data":{"type":"int","value":512}}}}}}